{
  "timestamp": 1761315024983,
  "hostname": "Musta",
  "uptime_seconds": 4356,
  "cpu_usage_pct": 15.94202995300293,
  "load_avg_one": 0.98,
  "load_avg_five": 1.03,
  "load_avg_fifteen": 1.01,
  "mem_used_mb": 2705184,
  "mem_total_mb": 16225484,
  "mem_available_mb": 13520300,
  "disks": [
    {
      "name": "/dev/sdf",
      "mount_point": "/",
      "filesystem": "ext4",
      "total_gb": 1006.853931427002,
      "used_gb": 67.96284484863281,
      "used_pct": 6.750020308537693
    },
    {
      "name": "C:\\134",
      "mount_point": "/mnt/c",
      "filesystem": "9p",
      "total_gb": 231.89257431030273,
      "used_gb": 160.88317489624023,
      "used_pct": 69.37832113630228
    },
    {
      "name": "D:\\134",
      "mount_point": "/mnt/d",
      "filesystem": "9p",
      "total_gb": 244.13964462280273,
      "used_gb": 6.156135559082031,
      "used_pct": 2.521563250652428
    },
    {
      "name": "D:\\134",
      "mount_point": "/mnt/d",
      "filesystem": "9p",
      "total_gb": 244.13964462280273,
      "used_gb": 6.156135559082031,
      "used_pct": 2.521563250652428
    }
  ],
  "network": [
    {
      "name": "lo",
      "received_total_bytes": 866083438,
      "transmitted_total_bytes": 866083438,
      "received_kbps": 21293.0,
      "transmitted_kbps": 21293.0
    },
    {
      "name": "eth0",
      "received_total_bytes": 152606,
      "transmitted_total_bytes": 43995,
      "received_kbps": 0.703125,
      "transmitted_kbps": 0.703125
    }
  ],
  "top_processes": [
    {
      "pid": 4164,
      "name": "agent",
      "cpu_pct": 73.91304016113281,
      "memory_mb": 420816,
      "memory_pct": 2.5935497517362194,
      "virtual_memory_mb": 1795440,
      "status": "Sleeping",
      "disk_read_bytes_total": 4113612800,
      "disk_write_bytes_total": 57344,
      "disk_read_kbps": 43520.0,
      "disk_write_kbps": 0.0,
      "thread_count": 26
    },
    {
      "pid": 4202,
      "name": "tokio-runtime-w",
      "cpu_pct": 60.869564056396484,
      "memory_mb": 420816,
      "memory_pct": 2.5935497517362194,
      "virtual_memory_mb": 1795440,
      "status": "Running",
      "disk_read_bytes_total": 0,
      "disk_write_bytes_total": 0,
      "disk_read_kbps": 0.0,
      "disk_write_kbps": 0.0,
      "thread_count": null
    },
    {
      "pid": 4212,
      "name": "tokio-runtime-w",
      "cpu_pct": 4.34782600402832,
      "memory_mb": 420816,
      "memory_pct": 2.5935497517362194,
      "virtual_memory_mb": 1795440,
      "status": "Running",
      "disk_read_bytes_total": 0,
      "disk_write_bytes_total": 0,
      "disk_read_kbps": 0.0,
      "disk_write_kbps": 0.0,
      "thread_count": null
    },
    {
      "pid": 4216,
      "name": "tokio-runtime-w",
      "cpu_pct": 4.34782600402832,
      "memory_mb": 420816,
      "memory_pct": 2.5935497517362194,
      "virtual_memory_mb": 1795440,
      "status": "Running",
      "disk_read_bytes_total": 0,
      "disk_write_bytes_total": 0,
      "disk_read_kbps": 0.0,
      "disk_write_kbps": 0.0,
      "thread_count": null
    },
    {
      "pid": 3889,
      "name": "docker-compose",
      "cpu_pct": 4.34782600402832,
      "memory_mb": 53792,
      "memory_pct": 0.33152786074054863,
      "virtual_memory_mb": 1293404,
      "status": "Sleeping",
      "disk_read_bytes_total": 110592,
      "disk_write_bytes_total": 0,
      "disk_read_kbps": 0.0,
      "disk_write_kbps": 0.0,
      "thread_count": null
    },
    {
      "pid": 4207,
      "name": "tokio-runtime-w",
      "cpu_pct": 4.34782600402832,
      "memory_mb": 420816,
      "memory_pct": 2.5935497517362194,
      "virtual_memory_mb": 1795440,
      "status": "Running",
      "disk_read_bytes_total": 0,
      "disk_write_bytes_total": 0,
      "disk_read_kbps": 0.0,
      "disk_write_kbps": 0.0,
      "thread_count": null
    },
    {
      "pid": 4210,
      "name": "tokio-runtime-w",
      "cpu_pct": 4.34782600402832,
      "memory_mb": 420816,
      "memory_pct": 2.5935497517362194,
      "virtual_memory_mb": 1795440,
      "status": "Running",
      "disk_read_bytes_total": 0,
      "disk_write_bytes_total": 0,
      "disk_read_kbps": 0.0,
      "disk_write_kbps": 0.0,
      "thread_count": null
    },
    {
      "pid": 3885,
      "name": "docker-compose",
      "cpu_pct": 4.34782600402832,
      "memory_mb": 53792,
      "memory_pct": 0.33152786074054863,
      "virtual_memory_mb": 1293404,
      "status": "Sleeping",
      "disk_read_bytes_total": 2330624,
      "disk_write_bytes_total": 0,
      "disk_read_kbps": 0.0,
      "disk_write_kbps": 0.0,
      "thread_count": 16
    },
    {
      "pid": 4211,
      "name": "tokio-runtime-w",
      "cpu_pct": 4.34782600402832,
      "memory_mb": 420816,
      "memory_pct": 2.5935497517362194,
      "virtual_memory_mb": 1795440,
      "status": "Running",
      "disk_read_bytes_total": 0,
      "disk_write_bytes_total": 0,
      "disk_read_kbps": 0.0,
      "disk_write_kbps": 0.0,
      "thread_count": null
    },
    {
      "pid": 88,
      "name": "systemd-udevd",
      "cpu_pct": 4.34782600402832,
      "memory_mb": 6784,
      "memory_pct": 0.04181077125341839,
      "virtual_memory_mb": 25796,
      "status": "Sleeping",
      "disk_read_bytes_total": 0,
      "disk_write_bytes_total": 0,
      "disk_read_kbps": 0.0,
      "disk_write_kbps": 0.0,
      "thread_count": 0
    },
    {
      "pid": 4218,
      "name": "tokio-runtime-w",
      "cpu_pct": 4.34782600402832,
      "memory_mb": 420816,
      "memory_pct": 2.5935497517362194,
      "virtual_memory_mb": 1795440,
      "status": "Running",
      "disk_read_bytes_total": 0,
      "disk_write_bytes_total": 0,
      "disk_read_kbps": 0.0,
      "disk_write_kbps": 0.0,
      "thread_count": null
    },
    {
      "pid": 3869,
      "name": "docker",
      "cpu_pct": 0.0,
      "memory_mb": 23620,
      "memory_pct": 0.14557346948787475,
      "virtual_memory_mb": 1255820,
      "status": "Sleeping",
      "disk_read_bytes_total": 0,
      "disk_write_bytes_total": 0,
      "disk_read_kbps": 0.0,
      "disk_write_kbps": 0.0,
      "thread_count": null
    },
    {
      "pid": 4729,
      "name": "tokio-runtime-w",
      "cpu_pct": 0.0,
      "memory_mb": 420816,
      "memory_pct": 2.5935497517362194,
      "virtual_memory_mb": 1795440,
      "status": "Sleeping",
      "disk_read_bytes_total": 0,
      "disk_write_bytes_total": 0,
      "disk_read_kbps": 0.0,
      "disk_write_kbps": 0.0,
      "thread_count": null
    },
    {
      "pid": 2967,
      "name": "DelayedTaskSche",
      "cpu_pct": 0.0,
      "memory_mb": 567744,
      "memory_pct": 3.4990882244252313,
      "virtual_memory_mb": 28398080,
      "status": "Sleeping",
      "disk_read_bytes_total": 0,
      "disk_write_bytes_total": 0,
      "disk_read_kbps": 0.0,
      "disk_write_kbps": 0.0,
      "thread_count": null
    },
    {
      "pid": 317,
      "name": "rs:main Q:Reg",
      "cpu_pct": 0.0,
      "memory_mb": 5504,
      "memory_pct": 0.03392194648862246,
      "virtual_memory_mb": 222508,
      "status": "Sleeping",
      "disk_read_bytes_total": 0,
      "disk_write_bytes_total": 0,
      "disk_read_kbps": 0.0,
      "disk_write_kbps": 0.0,
      "thread_count": null
    },
    {
      "pid": 4322,
      "name": "docker",
      "cpu_pct": 0.0,
      "memory_mb": 23620,
      "memory_pct": 0.14557346948787475,
      "virtual_memory_mb": 1255820,
      "status": "Sleeping",
      "disk_read_bytes_total": 0,
      "disk_write_bytes_total": 0,
      "disk_read_kbps": 0.0,
      "disk_write_kbps": 0.0,
      "thread_count": null
    },
    {
      "pid": 6520,
      "name": "libuv-worker",
      "cpu_pct": 0.0,
      "memory_mb": 86936,
      "memory_pct": 0.5357991169939831,
      "virtual_memory_mb": 2811280,
      "status": "Sleeping",
      "disk_read_bytes_total": 0,
      "disk_write_bytes_total": 0,
      "disk_read_kbps": 0.0,
      "disk_write_kbps": 0.0,
      "thread_count": null
    },
    {
      "pid": 136,
      "name": "snapfuse",
      "cpu_pct": 0.0,
      "memory_mb": 1284,
      "memory_pct": 0.00791347734218591,
      "virtual_memory_mb": 152936,
      "status": "Sleeping",
      "disk_read_bytes_total": 0,
      "disk_write_bytes_total": 0,
      "disk_read_kbps": 0.0,
      "disk_write_kbps": 0.0,
      "thread_count": 2
    },
    {
      "pid": 2597,
      "name": "bash",
      "cpu_pct": 0.0,
      "memory_mb": 9600,
      "memory_pct": 0.059166185735969413,
      "virtual_memory_mb": 12740,
      "status": "Sleeping",
      "disk_read_bytes_total": 12288,
      "disk_write_bytes_total": 0,
      "disk_read_kbps": 0.0,
      "disk_write_kbps": 0.0,
      "thread_count": 0
    },
    {
      "pid": 6209,
      "name": "bash",
      "cpu_pct": 0.0,
      "memory_mb": 9452,
      "memory_pct": 0.058254040372539895,
      "virtual_memory_mb": 12740,
      "status": "Sleeping",
      "disk_read_bytes_total": 0,
      "disk_write_bytes_total": 0,
      "disk_read_kbps": 0.0,
      "disk_write_kbps": 0.0,
      "thread_count": 0
    },
    {
      "pid": 6521,
      "name": "libuv-worker",
      "cpu_pct": 0.0,
      "memory_mb": 86936,
      "memory_pct": 0.5357991169939831,
      "virtual_memory_mb": 2811280,
      "status": "Sleeping",
      "disk_read_bytes_total": 0,
      "disk_write_bytes_total": 0,
      "disk_read_kbps": 0.0,
      "disk_write_kbps": 0.0,
      "thread_count": null
    },
    {
      "pid": 4604,
      "name": "docker-compose",
      "cpu_pct": 0.0,
      "memory_mb": 53792,
      "memory_pct": 0.33152786074054863,
      "virtual_memory_mb": 1293404,
      "status": "Sleeping",
      "disk_read_bytes_total": 0,
      "disk_write_bytes_total": 0,
      "disk_read_kbps": 0.0,
      "disk_write_kbps": 0.0,
      "thread_count": null
    },
    {
      "pid": 304,
      "name": "wsl-pro-service",
      "cpu_pct": 0.0,
      "memory_mb": 12032,
      "memory_pct": 0.07415495278908167,
      "virtual_memory_mb": 1755840,
      "status": "Sleeping",
      "disk_read_bytes_total": 0,
      "disk_write_bytes_total": 0,
      "disk_read_kbps": 0.0,
      "disk_write_kbps": 0.0,
      "thread_count": null
    },
    {
      "pid": 915,
      "name": "docker-desktop-",
      "cpu_pct": 0.0,
      "memory_mb": 23280,
      "memory_pct": 0.14347800040972583,
      "virtual_memory_mb": 1248404,
      "status": "Sleeping",
      "disk_read_bytes_total": 0,
      "disk_write_bytes_total": 0,
      "disk_read_kbps": 0.0,
      "disk_write_kbps": 0.0,
      "thread_count": null
    },
    {
      "pid": 4184,
      "name": "DelayedTaskSche",
      "cpu_pct": 0.0,
      "memory_mb": 465872,
      "memory_pct": 2.871236383457036,
      "virtual_memory_mb": 1784172,
      "status": "Sleeping",
      "disk_read_bytes_total": 0,
      "disk_write_bytes_total": 0,
      "disk_read_kbps": 0.0,
      "disk_write_kbps": 0.0,
      "thread_count": null
    }
  ],
  "gpu_usage_pct": 22.0,
  "gpu_memory_usage_pct": 22.0,
  "gpus": [
    {
      "index": 0,
      "name": "Quadro T1000",
      "uuid": null,
      "gpu_usage_pct": 22.0,
      "memory_used_mb": 2139,
      "memory_total_mb": 4096,
      "memory_usage_pct": 52.2216796875,
      "temperature_celsius": 48.0
    }
  ],
  "cpu_per_core_usage_pct": [
    8.69565200805664,
    8.69565200805664,
    13.043478012084961,
    8.69565200805664,
    16.666667938232422,
    16.0,
    70.83332824707031,
    9.090909004211426,
    8.69565200805664,
    4.545454502105713,
    13.043478012084961,
    4.761904716491699
  ],
  "cpu_logical_cores": 12,
  "cpu_physical_cores": 6,
  "swap_total_mb": 4194304,
  "swap_used_mb": 0,
  "swap_free_mb": 4194304
}