{
  "timestamp": 1761314366942,
  "hostname": "Musta",
  "uptime_seconds": 3675,
  "cpu_usage_pct": 9.963099479675293,
  "load_avg_one": 0.92,
  "load_avg_five": 1.03,
  "load_avg_fifteen": 1.02,
  "mem_used_mb": 2694812,
  "mem_total_mb": 16225484,
  "mem_available_mb": 13530672,
  "disks": [
    {
      "name": "/dev/sdf",
      "mount_point": "/",
      "filesystem": "ext4",
      "total_gb": 1006.853931427002,
      "used_gb": 67.96284866333008,
      "used_pct": 6.75002068741065
    },
    {
      "name": "C:\\134",
      "mount_point": "/mnt/c",
      "filesystem": "9p",
      "total_gb": 231.89257431030273,
      "used_gb": 160.8582305908203,
      "used_pct": 69.3675642996532
    },
    {
      "name": "D:\\134",
      "mount_point": "/mnt/d",
      "filesystem": "9p",
      "total_gb": 244.13964462280273,
      "used_gb": 6.146392822265625,
      "used_pct": 2.5175726096275106
    },
    {
      "name": "D:\\134",
      "mount_point": "/mnt/d",
      "filesystem": "9p",
      "total_gb": 244.13964462280273,
      "used_gb": 6.146392822265625,
      "used_pct": 2.5175726096275106
    }
  ],
  "network": [
    {
      "name": "lo",
      "received_total_bytes": 785463813,
      "transmitted_total_bytes": 785463813,
      "received_kbps": 0.0,
      "transmitted_kbps": 0.0
    },
    {
      "name": "eth0",
      "received_total_bytes": 132736,
      "transmitted_total_bytes": 40791,
      "received_kbps": 0.0,
      "transmitted_kbps": 0.0
    }
  ],
  "top_processes": [
    {
      "pid": 4164,
      "name": "agent",
      "cpu_pct": 13.28413200378418,
      "memory_mb": 410076,
      "memory_pct": 2.5273575814441034,
      "virtual_memory_mb": 1795440,
      "status": "Sleeping",
      "disk_read_bytes_total": 3434004480,
      "disk_write_bytes_total": 57344,
      "disk_read_kbps": 43520.0,
      "disk_write_kbps": 0.0,
      "thread_count": 26
    },
    {
      "pid": 3885,
      "name": "docker-compose",
      "cpu_pct": 8.856088638305664,
      "memory_mb": 53636,
      "memory_pct": 0.3305664102223391,
      "virtual_memory_mb": 1293404,
      "status": "Sleeping",
      "disk_read_bytes_total": 2199552,
      "disk_write_bytes_total": 0,
      "disk_read_kbps": 0.0,
      "disk_write_kbps": 0.0,
      "thread_count": 16
    },
    {
      "pid": 4211,
      "name": "tokio-runtime-w",
      "cpu_pct": 4.428044319152832,
      "memory_mb": 410076,
      "memory_pct": 2.5273575814441034,
      "virtual_memory_mb": 1795440,
      "status": "Running",
      "disk_read_bytes_total": 0,
      "disk_write_bytes_total": 0,
      "disk_read_kbps": 0.0,
      "disk_write_kbps": 0.0,
      "thread_count": null
    },
    {
      "pid": 4215,
      "name": "tokio-runtime-w",
      "cpu_pct": 4.428044319152832,
      "memory_mb": 410076,
      "memory_pct": 2.5273575814441034,
      "virtual_memory_mb": 1795440,
      "status": "Running",
      "disk_read_bytes_total": 0,
      "disk_write_bytes_total": 0,
      "disk_read_kbps": 0.0,
      "disk_write_kbps": 0.0,
      "thread_count": null
    },
    {
      "pid": 2966,
      "name": "webpack",
      "cpu_pct": 4.428044319152832,
      "memory_mb": 567488,
      "memory_pct": 3.4975104594722723,
      "virtual_memory_mb": 28398080,
      "status": "Sleeping",
      "disk_read_bytes_total": 21663744,
      "disk_write_bytes_total": 2555904,
      "disk_read_kbps": 0.0,
      "disk_write_kbps": 0.0,
      "thread_count": 10
    },
    {
      "pid": 3896,
      "name": "docker-compose",
      "cpu_pct": 4.428044319152832,
      "memory_mb": 53636,
      "memory_pct": 0.3305664102223391,
      "virtual_memory_mb": 1293404,
      "status": "Sleeping",
      "disk_read_bytes_total": 16384,
      "disk_write_bytes_total": 0,
      "disk_read_kbps": 0.0,
      "disk_write_kbps": 0.0,
      "thread_count": null
    },
    {
      "pid": 4213,
      "name": "tokio-runtime-w",
      "cpu_pct": 4.428044319152832,
      "memory_mb": 410076,
      "memory_pct": 2.5273575814441034,
      "virtual_memory_mb": 1795440,
      "status": "Running",
      "disk_read_bytes_total": 0,
      "disk_write_bytes_total": 0,
      "disk_read_kbps": 0.0,
      "disk_write_kbps": 0.0,
      "thread_count": null
    },
    {
      "pid": 3871,
      "name": "docker",
      "cpu_pct": 0.0,
      "memory_mb": 23620,
      "memory_pct": 0.14557346948787475,
      "virtual_memory_mb": 1255820,
      "status": "Sleeping",
      "disk_read_bytes_total": 0,
      "disk_write_bytes_total": 0,
      "disk_read_kbps": 0.0,
      "disk_write_kbps": 0.0,
      "thread_count": null
    },
    {
      "pid": 145,
      "name": "snapfuse",
      "cpu_pct": 0.0,
      "memory_mb": 1540,
      "memory_pct": 0.009491242295145093,
      "virtual_memory_mb": 153068,
      "status": "Sleeping",
      "disk_read_bytes_total": 0,
      "disk_write_bytes_total": 0,
      "disk_read_kbps": 0.0,
      "disk_write_kbps": 0.0,
      "thread_count": null
    },
    {
      "pid": 4182,
      "name": "V8Worker",
      "cpu_pct": 0.0,
      "memory_mb": 108372,
      "memory_pct": 0.6679122792269248,
      "virtual_memory_mb": 1462352,
      "status": "Sleeping",
      "disk_read_bytes_total": 0,
      "disk_write_bytes_total": 0,
      "disk_read_kbps": 0.0,
      "disk_write_kbps": 0.0,
      "thread_count": null
    },
    {
      "pid": 4198,
      "name": "tokio-runtime-w",
      "cpu_pct": 0.0,
      "memory_mb": 410076,
      "memory_pct": 2.5273575814441034,
      "virtual_memory_mb": 1795440,
      "status": "Sleeping",
      "disk_read_bytes_total": 40960,
      "disk_write_bytes_total": 0,
      "disk_read_kbps": 0.0,
      "disk_write_kbps": 0.0,
      "thread_count": null
    },
    {
      "pid": 43,
      "name": "systemd-journal",
      "cpu_pct": 0.0,
      "memory_mb": 15160,
      "memory_pct": 0.09343326830805171,
      "virtual_memory_mb": 66812,
      "status": "Sleeping",
      "disk_read_bytes_total": 0,
      "disk_write_bytes_total": 0,
      "disk_read_kbps": 0.0,
      "disk_write_kbps": 0.0,
      "thread_count": 0
    },
    {
      "pid": 143,
      "name": "snapfuse",
      "cpu_pct": 0.0,
      "memory_mb": 1540,
      "memory_pct": 0.009491242295145093,
      "virtual_memory_mb": 153068,
      "status": "Sleeping",
      "disk_read_bytes_total": 0,
      "disk_write_bytes_total": 0,
      "disk_read_kbps": 0.0,
      "disk_write_kbps": 0.0,
      "thread_count": 2
    },
    {
      "pid": 6486,
      "name": "V8Worker",
      "cpu_pct": 0.0,
      "memory_mb": 86588,
      "memory_pct": 0.5336543427610542,
      "virtual_memory_mb": 2811280,
      "status": "Sleeping",
      "disk_read_bytes_total": 0,
      "disk_write_bytes_total": 0,
      "disk_read_kbps": 0.0,
      "disk_write_kbps": 0.0,
      "thread_count": null
    },
    {
      "pid": 2967,
      "name": "DelayedTaskSche",
      "cpu_pct": 0.0,
      "memory_mb": 567488,
      "memory_pct": 3.4975104594722723,
      "virtual_memory_mb": 28398080,
      "status": "Sleeping",
      "disk_read_bytes_total": 0,
      "disk_write_bytes_total": 0,
      "disk_read_kbps": 0.0,
      "disk_write_kbps": 0.0,
      "thread_count": null
    },
    {
      "pid": 6209,
      "name": "bash",
      "cpu_pct": 0.0,
      "memory_mb": 9452,
      "memory_pct": 0.058254040372539895,
      "virtual_memory_mb": 12740,
      "status": "Sleeping",
      "disk_read_bytes_total": 0,
      "disk_write_bytes_total": 0,
      "disk_read_kbps": 0.0,
      "disk_write_kbps": 0.0,
      "thread_count": 0
    },
    {
      "pid": 4181,
      "name": "V8Worker",
      "cpu_pct": 0.0,
      "memory_mb": 108372,
      "memory_pct": 0.6679122792269248,
      "virtual_memory_mb": 1462352,
      "status": "Sleeping",
      "disk_read_bytes_total": 0,
      "disk_write_bytes_total": 0,
      "disk_read_kbps": 0.0,
      "disk_write_kbps": 0.0,
      "thread_count": null
    },
    {
      "pid": 6523,
      "name": "libuv-worker",
      "cpu_pct": 0.0,
      "memory_mb": 86588,
      "memory_pct": 0.5336543427610542,
      "virtual_memory_mb": 2811280,
      "status": "Sleeping",
      "disk_read_bytes_total": 0,
      "disk_write_bytes_total": 0,
      "disk_read_kbps": 0.0,
      "disk_write_kbps": 0.0,
      "thread_count": null
    },
    {
      "pid": 4196,
      "name": "tokio-runtime-w",
      "cpu_pct": 0.0,
      "memory_mb": 410076,
      "memory_pct": 2.5273575814441034,
      "virtual_memory_mb": 1795440,
      "status": "Sleeping",
      "disk_read_bytes_total": 212992,
      "disk_write_bytes_total": 0,
      "disk_read_kbps": 0.0,
      "disk_write_kbps": 0.0,
      "thread_count": null
    },
    {
      "pid": 4195,
      "name": "tokio-runtime-w",
      "cpu_pct": 0.0,
      "memory_mb": 410076,
      "memory_pct": 2.5273575814441034,
      "virtual_memory_mb": 1795440,
      "status": "Sleeping",
      "disk_read_bytes_total": 0,
      "disk_write_bytes_total": 0,
      "disk_read_kbps": 0.0,
      "disk_write_kbps": 0.0,
      "thread_count": null
    },
    {
      "pid": 742,
      "name": "login",
      "cpu_pct": 0.0,
      "memory_mb": 3968,
      "memory_pct": 0.024455356770867357,
      "virtual_memory_mb": 6664,
      "status": "Sleeping",
      "disk_read_bytes_total": 0,
      "disk_write_bytes_total": 0,
      "disk_read_kbps": 0.0,
      "disk_write_kbps": 0.0,
      "thread_count": 0
    },
    {
      "pid": 487,
      "name": "bash",
      "cpu_pct": 0.0,
      "memory_mb": 9080,
      "memory_pct": 0.05596135067527107,
      "virtual_memory_mb": 12624,
      "status": "Sleeping",
      "disk_read_bytes_total": 2985984,
      "disk_write_bytes_total": 0,
      "disk_read_kbps": 0.0,
      "disk_write_kbps": 0.0,
      "thread_count": 0
    },
    {
      "pid": 6478,
      "name": "libuv-worker",
      "cpu_pct": 0.0,
      "memory_mb": 70084,
      "memory_pct": 0.4319378084499667,
      "virtual_memory_mb": 1520496,
      "status": "Sleeping",
      "disk_read_bytes_total": 0,
      "disk_write_bytes_total": 0,
      "disk_read_kbps": 0.0,
      "disk_write_kbps": 0.0,
      "thread_count": null
    },
    {
      "pid": 97,
      "name": "snapfuse",
      "cpu_pct": 0.0,
      "memory_mb": 1412,
      "memory_pct": 0.008702359818665501,
      "virtual_memory_mb": 152936,
      "status": "Sleeping",
      "disk_read_bytes_total": 0,
      "disk_write_bytes_total": 0,
      "disk_read_kbps": 0.0,
      "disk_write_kbps": 0.0,
      "thread_count": 2
    },
    {
      "pid": 9,
      "name": "Interop",
      "cpu_pct": 0.0,
      "memory_mb": 1920,
      "memory_pct": 0.011833237147193884,
      "virtual_memory_mb": 3072,
      "status": "Sleeping",
      "disk_read_bytes_total": 0,
      "disk_write_bytes_total": 0,
      "disk_read_kbps": 0.0,
      "disk_write_kbps": 0.0,
      "thread_count": null
    }
  ],
  "gpu_usage_pct": 12.0,
  "gpu_memory_usage_pct": 13.0,
  "gpus": [
    {
      "index": 0,
      "name": "Quadro T1000",
      "uuid": null,
      "gpu_usage_pct": 12.0,
      "memory_used_mb": 2069,
      "memory_total_mb": 4096,
      "memory_usage_pct": 50.5126953125,
      "temperature_celsius": 50.0
    }
  ],
  "cpu_per_core_usage_pct": [
    4.761904716491699,
    12.5,
    16.666667938232422,
    13.043478012084961,
    8.69565200805664,
    8.69565200805664,
    4.545454502105713,
    4.545454502105713,
    9.090909004211426,
    12.5,
    8.69565200805664,
    13.043478012084961
  ],
  "cpu_logical_cores": 12,
  "cpu_physical_cores": 6,
  "swap_total_mb": 4194304,
  "swap_used_mb": 0,
  "swap_free_mb": 4194304
}