{
  "timestamp": 1761293290955,
  "hostname": "Musta",
  "uptime_seconds": 7835,
  "cpu_usage_pct": 4.119850158691406,
  "load_avg_one": 0.9,
  "load_avg_five": 1.12,
  "load_avg_fifteen": 1.08,
  "mem_used_mb": 2178036,
  "mem_total_mb": 16225488,
  "mem_available_mb": 14047452,
  "disks": [
    {
      "name": "/dev/sdd",
      "mount_point": "/",
      "filesystem": "ext4",
      "total_gb": 1006.853931427002,
      "used_gb": 68.0289421081543,
      "used_pct": 6.75658504026872
    },
    {
      "name": "C:\\134",
      "mount_point": "/mnt/c",
      "filesystem": "9p",
      "total_gb": 231.89257431030273,
      "used_gb": 159.72315979003906,
      "used_pct": 68.8780829938558
    },
    {
      "name": "D:\\134",
      "mount_point": "/mnt/d",
      "filesystem": "9p",
      "total_gb": 244.13964462280273,
      "used_gb": 6.291316986083984,
      "used_pct": 2.5769337854997323
    },
    {
      "name": "D:\\134",
      "mount_point": "/mnt/d",
      "filesystem": "9p",
      "total_gb": 244.13964462280273,
      "used_gb": 6.291316986083984,
      "used_pct": 2.5769337854997323
    }
  ],
  "network": [
    {
      "name": "lo",
      "received_total_bytes": 1373465065,
      "transmitted_total_bytes": 1373465065,
      "received_kbps": 30501.09375,
      "transmitted_kbps": 30501.09375
    },
    {
      "name": "eth0",
      "received_total_bytes": 59908799,
      "transmitted_total_bytes": 21833545,
      "received_kbps": 0.0,
      "transmitted_kbps": 0.0
    }
  ],
  "top_processes": [
    {
      "pid": 11822,
      "name": "agent",
      "cpu_pct": 13.483145713806152,
      "memory_mb": 307692,
      "memory_pct": 1.8963497430709015,
      "virtual_memory_mb": 1727768,
      "status": "Sleeping",
      "disk_read_bytes_total": 759607296,
      "disk_write_bytes_total": 57344,
      "disk_read_kbps": 43520.0,
      "disk_write_kbps": 0.0,
      "thread_count": 25
    },
    {
      "pid": 11856,
      "name": "tokio-runtime-w",
      "cpu_pct": 4.494381904602051,
      "memory_mb": 307692,
      "memory_pct": 1.8963497430709015,
      "virtual_memory_mb": 1727768,
      "status": "Running",
      "disk_read_bytes_total": 0,
      "disk_write_bytes_total": 0,
      "disk_read_kbps": 0.0,
      "disk_write_kbps": 0.0,
      "thread_count": null
    },
    {
      "pid": 11853,
      "name": "tokio-runtime-w",
      "cpu_pct": 4.494381904602051,
      "memory_mb": 307692,
      "memory_pct": 1.8963497430709015,
      "virtual_memory_mb": 1727768,
      "status": "Running",
      "disk_read_bytes_total": 0,
      "disk_write_bytes_total": 0,
      "disk_read_kbps": 0.0,
      "disk_write_kbps": 0.0,
      "thread_count": null
    },
    {
      "pid": 11851,
      "name": "tokio-runtime-w",
      "cpu_pct": 4.494381904602051,
      "memory_mb": 307692,
      "memory_pct": 1.8963497430709015,
      "virtual_memory_mb": 1727768,
      "status": "Running",
      "disk_read_bytes_total": 0,
      "disk_write_bytes_total": 0,
      "disk_read_kbps": 0.0,
      "disk_write_kbps": 0.0,
      "thread_count": null
    },
    {
      "pid": 11854,
      "name": "tokio-runtime-w",
      "cpu_pct": 4.494381904602051,
      "memory_mb": 307692,
      "memory_pct": 1.8963497430709015,
      "virtual_memory_mb": 1727768,
      "status": "Running",
      "disk_read_bytes_total": 0,
      "disk_write_bytes_total": 0,
      "disk_read_kbps": 0.0,
      "disk_write_kbps": 0.0,
      "thread_count": null
    },
    {
      "pid": 11149,
      "name": "SignalInspector",
      "cpu_pct": 0.0,
      "memory_mb": 70408,
      "memory_pct": 0.43393456024250243,
      "virtual_memory_mb": 1520640,
      "status": "Sleeping",
      "disk_read_bytes_total": 0,
      "disk_write_bytes_total": 0,
      "disk_read_kbps": 0.0,
      "disk_write_kbps": 0.0,
      "thread_count": null
    },
    {
      "pid": 2320,
      "name": "systemd",
      "cpu_pct": 0.0,
      "memory_mb": 11264,
      "memory_pct": 0.06942164081598039,
      "virtual_memory_mb": 20444,
      "status": "Sleeping",
      "disk_read_bytes_total": 0,
      "disk_write_bytes_total": 0,
      "disk_read_kbps": 0.0,
      "disk_write_kbps": 0.0,
      "thread_count": 0
    },
    {
      "pid": 373,
      "name": "snapd",
      "cpu_pct": 0.0,
      "memory_mb": 40520,
      "memory_pct": 0.24973054739555445,
      "virtual_memory_mb": 2514744,
      "status": "Sleeping",
      "disk_read_bytes_total": 0,
      "disk_write_bytes_total": 0,
      "disk_read_kbps": 0.0,
      "disk_write_kbps": 0.0,
      "thread_count": null
    },
    {
      "pid": 2348,
      "name": "bash",
      "cpu_pct": 0.0,
      "memory_mb": 5248,
      "memory_pct": 0.03234417356199086,
      "virtual_memory_mb": 8532,
      "status": "Sleeping",
      "disk_read_bytes_total": 0,
      "disk_write_bytes_total": 0,
      "disk_read_kbps": 0.0,
      "disk_write_kbps": 0.0,
      "thread_count": 0
    },
    {
      "pid": 11777,
      "name": "docker",
      "cpu_pct": 0.0,
      "memory_mb": 23552,
      "memory_pct": 0.145154339887959,
      "virtual_memory_mb": 1256140,
      "status": "Sleeping",
      "disk_read_bytes_total": 0,
      "disk_write_bytes_total": 0,
      "disk_read_kbps": 0.0,
      "disk_write_kbps": 0.0,
      "thread_count": null
    },
    {
      "pid": 288,
      "name": "in:imklog",
      "cpu_pct": 0.0,
      "memory_mb": 5504,
      "memory_pct": 0.03392193812599042,
      "virtual_memory_mb": 222508,
      "status": "Sleeping",
      "disk_read_bytes_total": 0,
      "disk_write_bytes_total": 0,
      "disk_read_kbps": 0.0,
      "disk_write_kbps": 0.0,
      "thread_count": null
    },
    {
      "pid": 2465,
      "name": "docker-desktop-",
      "cpu_pct": 0.0,
      "memory_mb": 23616,
      "memory_pct": 0.14554878102895888,
      "virtual_memory_mb": 1249452,
      "status": "Sleeping",
      "disk_read_bytes_total": 0,
      "disk_write_bytes_total": 0,
      "disk_read_kbps": 0.0,
      "disk_write_kbps": 0.0,
      "thread_count": 15
    },
    {
      "pid": 3800,
      "name": "V8Worker",
      "cpu_pct": 0.0,
      "memory_mb": 51072,
      "memory_pct": 0.3147640305179111,
      "virtual_memory_mb": 1414764,
      "status": "Stopped",
      "disk_read_bytes_total": 0,
      "disk_write_bytes_total": 0,
      "disk_read_kbps": 0.0,
      "disk_write_kbps": 0.0,
      "thread_count": null
    },
    {
      "pid": 149,
      "name": "snapfuse",
      "cpu_pct": 0.0,
      "memory_mb": 1540,
      "memory_pct": 0.009491239955309818,
      "virtual_memory_mb": 153068,
      "status": "Sleeping",
      "disk_read_bytes_total": 0,
      "disk_write_bytes_total": 0,
      "disk_read_kbps": 0.0,
      "disk_write_kbps": 0.0,
      "thread_count": null
    },
    {
      "pid": 2470,
      "name": "docker-desktop-",
      "cpu_pct": 0.0,
      "memory_mb": 23616,
      "memory_pct": 0.14554878102895888,
      "virtual_memory_mb": 1249452,
      "status": "Sleeping",
      "disk_read_bytes_total": 0,
      "disk_write_bytes_total": 0,
      "disk_read_kbps": 0.0,
      "disk_write_kbps": 0.0,
      "thread_count": null
    },
    {
      "pid": 248,
      "name": "systemd-logind",
      "cpu_pct": 0.0,
      "memory_mb": 8192,
      "memory_pct": 0.050488466047985736,
      "virtual_memory_mb": 18152,
      "status": "Sleeping",
      "disk_read_bytes_total": 0,
      "disk_write_bytes_total": 0,
      "disk_read_kbps": 0.0,
      "disk_write_kbps": 0.0,
      "thread_count": 0
    },
    {
      "pid": 413,
      "name": "login",
      "cpu_pct": 0.0,
      "memory_mb": 4352,
      "memory_pct": 0.026821997587992422,
      "virtual_memory_mb": 6820,
      "status": "Sleeping",
      "disk_read_bytes_total": 0,
      "disk_write_bytes_total": 0,
      "disk_read_kbps": 0.0,
      "disk_write_kbps": 0.0,
      "thread_count": 0
    },
    {
      "pid": 104,
      "name": "snapfuse",
      "cpu_pct": 0.0,
      "memory_mb": 1284,
      "memory_pct": 0.007913475391310265,
      "virtual_memory_mb": 152936,
      "status": "Sleeping",
      "disk_read_bytes_total": 0,
      "disk_write_bytes_total": 0,
      "disk_read_kbps": 0.0,
      "disk_write_kbps": 0.0,
      "thread_count": 2
    },
    {
      "pid": 11806,
      "name": "docker-compose",
      "cpu_pct": 0.0,
      "memory_mb": 53236,
      "memory_pct": 0.3281010715979698,
      "virtual_memory_mb": 1293404,
      "status": "Sleeping",
      "disk_read_bytes_total": 225280,
      "disk_write_bytes_total": 0,
      "disk_read_kbps": 0.0,
      "disk_write_kbps": 0.0,
      "thread_count": null
    },
    {
      "pid": 287,
      "name": "in:imuxsock",
      "cpu_pct": 0.0,
      "memory_mb": 5504,
      "memory_pct": 0.03392193812599042,
      "virtual_memory_mb": 222508,
      "status": "Sleeping",
      "disk_read_bytes_total": 0,
      "disk_write_bytes_total": 0,
      "disk_read_kbps": 0.0,
      "disk_write_kbps": 0.0,
      "thread_count": null
    },
    {
      "pid": 253,
      "name": "agetty",
      "cpu_pct": 0.0,
      "memory_mb": 2176,
      "memory_pct": 0.013410998793996211,
      "virtual_memory_mb": 5720,
      "status": "Sleeping",
      "disk_read_bytes_total": 0,
      "disk_write_bytes_total": 0,
      "disk_read_kbps": 0.0,
      "disk_write_kbps": 0.0,
      "thread_count": 0
    },
    {
      "pid": 11846,
      "name": "tokio-runtime-w",
      "cpu_pct": 0.0,
      "memory_mb": 307692,
      "memory_pct": 1.8963497430709015,
      "virtual_memory_mb": 1727768,
      "status": "Sleeping",
      "disk_read_bytes_total": 139264,
      "disk_write_bytes_total": 0,
      "disk_read_kbps": 0.0,
      "disk_write_kbps": 0.0,
      "thread_count": null
    },
    {
      "pid": 11859,
      "name": "tokio-runtime-w",
      "cpu_pct": 0.0,
      "memory_mb": 307692,
      "memory_pct": 1.8963497430709015,
      "virtual_memory_mb": 1727768,
      "status": "Running",
      "disk_read_bytes_total": 0,
      "disk_write_bytes_total": 0,
      "disk_read_kbps": 0.0,
      "disk_write_kbps": 0.0,
      "thread_count": null
    },
    {
      "pid": 2272,
      "name": "SessionLeader",
      "cpu_pct": 0.0,
      "memory_mb": 1032,
      "memory_pct": 0.006360363398623204,
      "virtual_memory_mb": 3080,
      "status": "Sleeping",
      "disk_read_bytes_total": 0,
      "disk_write_bytes_total": 0,
      "disk_read_kbps": 0.0,
      "disk_write_kbps": 0.0,
      "thread_count": 0
    },
    {
      "pid": 5170,
      "name": "docker-desktop-",
      "cpu_pct": 0.0,
      "memory_mb": 23616,
      "memory_pct": 0.14554878102895888,
      "virtual_memory_mb": 1249452,
      "status": "Sleeping",
      "disk_read_bytes_total": 0,
      "disk_write_bytes_total": 0,
      "disk_read_kbps": 0.0,
      "disk_write_kbps": 0.0,
      "thread_count": null
    }
  ],
  "gpu_usage_pct": 0.0,
  "gpu_memory_usage_pct": 10.0,
  "gpus": [
    {
      "index": 0,
      "name": "Quadro T1000",
      "uuid": null,
      "gpu_usage_pct": 0.0,
      "memory_used_mb": 1592,
      "memory_total_mb": 4096,
      "memory_usage_pct": 38.8671875,
      "temperature_celsius": 51.0
    }
  ],
  "cpu_per_core_usage_pct": [
    8.69565200805664,
    8.333333969116211,
    0.0,
    8.69565200805664,
    4.545454502105713,
    4.545454502105713,
    8.69565200805664,
    0.0,
    4.545454502105713,
    8.333333969116211,
    0.0,
    4.34782600402832
  ],
  "cpu_logical_cores": 12,
  "cpu_physical_cores": 6,
  "swap_total_mb": 4194304,
  "swap_used_mb": 0,
  "swap_free_mb": 4194304
}